polidoro_install/__init__.py
polidoro_install/installer.py
polidoro_install/main.py
polidoro_install-0.3.0.data/scripts/polinstall
polidoro_install-0.3.0.dist-info/LICENSE
polidoro_install-0.3.0.dist-info/METADATA
polidoro_install-0.3.0.dist-info/WHEEL
polidoro_install-0.3.0.dist-info/top_level.txt
polidoro_install-0.3.0.dist-info/RECORD
