Metadata-Version: 2.1
Name: polidoro-install
Version: 0.3.0
Summary: Polidoro Install.
Home-page: https://github.com/heitorpolidoro/polidoro-install
Author: Heitor Polidoro
License: unlicense
Platform: UNKNOWN
Classifier: Programming Language :: Python :: 3
Classifier: License :: OSI Approved :: MIT License
Classifier: Operating System :: OS Independent
License-File: LICENSE
Requires-Dist: pyyaml
Requires-Dist: pydantic
Requires-Dist: requests
